[{"EQUIPMENT":"Cape du Tofu Fou","METIER":"TAILLEUR","LEVEL":"40","QUANTITY":"2"},
{"EQUIPMENT":"Dora Sombre de Brave","METIER":"TAILLEUR","LEVEL":"41","QUANTITY":"1"},
{"EQUIPMENT":"Dantgoule","METIER":"TAILLEUR","LEVEL":"41","QUANTITY":"1"},
{"EQUIPMENT":"Dantgoule","METIER":"TAILLEUR","LEVEL":"42","QUANTITY":"1"},
{"EQUIPMENT":"Dantgoule","METIER":"TAILLEUR","LEVEL":"43","QUANTITY":"3"},
{"EQUIPMENT":"Dantgoule","METIER":"TAILLEUR","LEVEL":"44","QUANTITY":"1"},
{"EQUIPMENT":"Abracape","METIER":"TAILLEUR","LEVEL":"44","QUANTITY":"1"},
{"EQUIPMENT":"Cape du Corbac","METIER":"TAILLEUR","LEVEL":"45","QUANTITY":"1"},
{"EQUIPMENT":"Cape du Corbac","METIER":"TAILLEUR","LEVEL":"46","QUANTITY":"1"},
{"EQUIPMENT":"Cape du Corbac","METIER":"TAILLEUR","LEVEL":"47","QUANTITY":"1"},
{"EQUIPMENT":"Cape du Corbac","METIER":"TAILLEUR","LEVEL":"48","QUANTITY":"2"},
{"EQUIPMENT":"Cape du Corbac","METIER":"TAILLEUR","LEVEL":"49","QUANTITY":"1"}]